{
  "lighthouse": {
    "performance": 93.0,
    "accessibility": 96.0,
    "best_practices": 100,
    "seo": 100
  },
  "accessibility": {
    "violations_count": 1,
    "passes_count": 40,
    "incomplete_count": 2,
    "violations": [
      {
        "id": "color-contrast",
        "impact": "serious",
        "description": "Ensure the contrast between foreground and background colors meets WCAG 2 AA minimum contrast ratio thresholds",
        "nodes": 1
      }
    ]
  },
  "css": {
    "total_css_bytes": 34692,
    "selector_count": 256,
    "unique_hex_colors": 20,
    "hex_colors_sample": [
      "#000",
      "#0a0e17",
      "#0f1420",
      "#22d3ee",
      "#28c840",
      "#333",
      "#34d399",
      "#3877e0",
      "#4a88e8",
      "#555",
      "#a78bfa",
      "#b0bcc8",
      "#c8d6e5",
      "#ccc",
      "#e8f0fa",
      "#f97316",
      "#fb7185",
      "#febc2e",
      "#ff5f57",
      "#fff"
    ],
    "rgb_color_count": 24,
    "hsl_color_count": 0,
    "font_families": [
      "Schibsted Grotesk",
      "var(--font-mono)",
      "var(--font-display)",
      "DM Mono",
      "Instrument Serif",
      "var(--font-body)",
      "var(--font-mono) !important"
    ],
    "unique_font_sizes": 17,
    "font_sizes_sample": [
      "0.8em",
      "11px",
      "12px",
      "13px",
      "14px",
      "16px",
      "18px",
      "9px",
      "clamp(28px, 4vw, 44px)",
      "clamp(32px, 5vw, 56px)",
      "clamp(48px, 8vw, 96px)",
      "var(--text-lg)",
      "var(--text-md)",
      "var(--text-sm)",
      "var(--text-xl)"
    ],
    "important_count": 12,
    "media_query_count": 9
  }
}